happinesspacket_schema/__init__.py
happinesspacket_schema/schema.py
happinesspacket_schema/tests/__init__.py
happinesspacket_schema/tests/test_schema.py
happinesspacket_schema-1.0.0.dist-info/DESCRIPTION.rst
happinesspacket_schema-1.0.0.dist-info/METADATA
happinesspacket_schema-1.0.0.dist-info/RECORD
happinesspacket_schema-1.0.0.dist-info/WHEEL
happinesspacket_schema-1.0.0.dist-info/entry_points.txt
happinesspacket_schema-1.0.0.dist-info/metadata.json
happinesspacket_schema-1.0.0.dist-info/top_level.txt
